compressor/__init__.py
compressor/cli.py
compressor/constants.py
compressor/core.py
compressor/lib.py
compressor/util.py
trenzalore-0.2.0.dist-info/LICENSE
trenzalore-0.2.0.dist-info/METADATA
trenzalore-0.2.0.dist-info/WHEEL
trenzalore-0.2.0.dist-info/entry_points.txt
trenzalore-0.2.0.dist-info/top_level.txt
trenzalore-0.2.0.dist-info/zip-safe
trenzalore-0.2.0.dist-info/RECORD
